{
    "date": {
        "month": "05", 
        "day": "01", 
        "year": "2019"
    }, 
    "content": "පෞද්ගලික අංශයේ සේවකයින්ගේ අවම මාසික වැටුප ඉහළ දැමීමට කැබිනට් මණ්ඩලයේ අනුමැතිය හිමිව තිබෙනවා.ඒ අනුව මේ වනවිට රුපියල් 10,000ක්ව පවතින අවම මාසික මූලික වැටුප රුපියල් 12,500ක් දක්වා ඉහළ නංවනු ඇති.මේ වනවිට රුපියල් 400ක්ව පවතින පෞද්ගලික අංශයේ දෛනික මූලික වැටුප රුපියල් 500ක් දක්වා ඉහළ නැංවීමටයි තීරණය කර ඇත්තේ.වර්තමානයේ පවතින ජීවන වියදමට ගැළපෙන පරිදි මෙම තීරණය ගෙන තිබෙනවා.", 
    "views": "6488", 
    "authors": [
        "තරංග රුක්ෂාන් ජයසේකර"
    ], 
    "title": "පෞද්ගලික අංශයේ සේවකයින්ගේ අවම වැටුප වැඩි කෙරේ"
}