{
    "date": {
        "month": "06", 
        "day": "10", 
        "year": "2019"
    }, 
    "content": "ලංකා ජර්මානු කාර්මික අභ්‍යාස ආයතනයේ අධ්‍යක්‍ෂක විදුහල්පති තනතුර සඳහා සුදුසු පුද්ගලයෙකු පත් කරන්නැයි එහි ආදි සිසුන් ජනාධිපති මෛතී‍්‍රපාල සිරිසේන මහතාගෙන් ඉල්ලීමක් කරනවා.ඒ,ලංකා ජර්මානු කාර්මික අභ්‍යාස ආයතනයේ එක්සත් අරාබි එමීර් රාජ්‍යයේ ආදි ශිෂ්‍ය සංගමය ජනාධිපතිවරයා වෙත ලිපියක් යොමු කරමින්.එහි දැක්වෙන්නේ එම ආයතනයේ හිටපු විදුහල්පතිවරයා විශ‍්‍රාම යාමෙන් පසු මේ දක්වා අධ්‍යක්‍ෂක විදුහල්පති තනතුර පුරප්පාඩුව පවතින බවයි.මේ හේතුවෙන් ලංකා ජර්මානු කාර්මික අභ්‍යාස ආයතනයේ කළමනාකරණ සහ ගුණාත්මකභාවය බිද වැටීමේ අවදානමක් මතුව ඇති බවද අදාළ ලිපිය මගින් පෙන්වා දෙනවා.", 
    "views": "1807", 
    "authors": [
        "හේමන්ත කහවලගේ"
    ], 
    "title": "ලංකා ජර්මානු කාර්මික අභ්‍යාස ආයතනය ගැන ජනපතිට ලිපියක්"
}