{
    "date": {
        "month": "06", 
        "day": "11", 
        "year": "2019"
    }, 
    "content": "රජය සතු ව්‍යාපාර 10ක් සමග සාමූහික අභිලාෂ ප‍්‍රකාශ අත්සන් තැබීම මුදල් අමාත්‍යාංශයේදී ඊයේ (10) සිදු කෙරුණා.පාඩු ලබන රාජ්‍ය ආයතන ලාභ ලබන ආයතන බවට පත් කිරීම මෙහි අරමුණයි.ශ‍්‍රී ලංකාවේ දළ දේශීය නිෂ්පාදිතය වැඩි කිරීමෙන් ආර්ථික ඉලක්ක සපුරා ගැනීම සඳහා උපාය මාර්ගික වැදගත්කමක් ඇති රාජ්‍ය ආයතන වෙත සාධනීය ලෙස දායක වීමට මෙම සාමූහික අභිලාෂ ප‍්‍රකාශය මගින් හැකි වනු ඇති බවයි මුදල් අමාත්‍යාංශය පවසන්නේ.රජය සතු ව්‍යාපාරවල කාර්යය සාධනය ඉහළ නැංවීමේ අරමුණින් 2017 වසරේදී රාජ්‍ය ව්‍යාපාර දෙපාර්තමේන්තුව විසින් මෙම සාමූහික අභිලාෂ ප‍්‍රකාශ සංකල්පය හඳුන්වා දී තිබෙනවා.", 
    "views": "819", 
    "authors": [
        "ලහිරු කපුගේ"
    ], 
    "title": "පාඩු ලබන රාජ්‍ය ආයතන ලාභ ලබන ආයතන බවට පත් කිරීමට පියවර තබයි"
}